LICENSE
MANIFEST.in
README.rst
setup.py
Yozuch.egg-info/PKG-INFO
Yozuch.egg-info/SOURCES.txt
Yozuch.egg-info/dependency_links.txt
Yozuch.egg-info/entry_points.txt
Yozuch.egg-info/requires.txt
Yozuch.egg-info/top_level.txt
tests/__init__.py
tests/test_cmd.py
tests/test_config.py
tests/test_loader.py
tests/test_paginator.py
tests/test_rstparser.py
tests/test_site.py
tests/test_validator.py
tests/compiled-data/.DS_Store
tests/compiled-data/atom.xml
tests/compiled-data/image.png
tests/compiled-data/index.html
tests/compiled-data/page.html
tests/compiled-data/paginated_index.html
tests/compiled-data/static.txt
tests/compiled-data/theme_static.txt
tests/compiled-data/url1.html
tests/compiled-data-validator/test.html
tests/compiled-data/archive/index.html
tests/compiled-data/blog/.DS_Store
tests/compiled-data/blog/2011/01/01/post-readmore/index.html
tests/compiled-data/blog/2013/09/20/post-file-metadata/index.html
tests/compiled-data/blog/2013/10/02/post/index.html
tests/compiled-data/documents/.DS_Store
tests/compiled-data/documents/page2/index.html
tests/compiled-data/documents/page3/index.html
tests/compiled-data/page/2/index.html
tests/compiled-data/page/3/index.html
tests/compiled-data/tag/tag-2/index.html
tests/compiled-data/tag/tag1/index.html
tests/compiled-data/tags/index.html
tests/data/.DS_Store
tests/data/config.py
tests/data/config.pyc
tests/data-invalid/config.py
tests/data-invalid/config.pyc
tests/data-invalid/__pycache__/config.cpython-34.pyc
tests/data-invalid/__pycache__/config.cpython-35.pyc
tests/data-invalid/__pycache__/config.cpython-36.pyc
tests/data/__pycache__/config.cpython-34.pyc
tests/data/__pycache__/config.cpython-35.pyc
tests/data/__pycache__/config.cpython-36.pyc
tests/data/assets/image.png
tests/data/assets/static.txt
tests/data/documents/page.rst
tests/data/documents/page2.rst
tests/data/documents/page3.rst
tests/data/pages/page.html
tests/data/posts/.DS_Store
tests/data/posts/2013-09-20-post-file-metadata.rst
tests/data/posts/post-error.rst
tests/data/posts/post-readmore.rst
tests/data/posts/post.rst
tests/data/posts/~draft.rst
tests/data/templates/template1.html
tests/data/themes/test/config.py
