Metadata-Version: 1.1
Name: Yozuch
Version: 0.8.0
Summary: reStructuredText based static blog generator
Home-page: https://github.com/akrylysov/yozuch
Author: Artem Krylysov
Author-email: artem@krylysov.com
License: BSD
Keywords: static blog generator reStructuredText
Platform: UNKNOWN
Classifier: Development Status :: 4 - Beta
Classifier: License :: OSI Approved :: BSD License
Classifier: Environment :: Console
Classifier: Environment :: Web Environment
Classifier: Intended Audience :: Developers
Classifier: Topic :: Internet
Classifier: Topic :: Text Processing
Classifier: Topic :: Communications
Classifier: Operating System :: OS Independent
Classifier: Programming Language :: Python
Classifier: Programming Language :: Python :: 3.6
